petab/C.py
petab/__init__.py
petab/calculate.py
petab/composite_problem.py
petab/conditions.py
petab/core.py
petab/format_version.py
petab/lint.py
petab/mapping.py
petab/measurements.py
petab/observables.py
petab/parameter_mapping.py
petab/parameters.py
petab/petablint.py
petab/problem.py
petab/sampling.py
petab/sbml.py
petab/simplify.py
petab/simulate.py
petab/version.py
petab/yaml.py
petab/models/__init__.py
petab/models/model.py
petab/models/pysb_model.py
petab/models/sbml_model.py
petab/schemas/petab_schema.v1.0.0.yaml
petab/schemas/petab_schema.v2.0.0.yaml
petab/visualize/__init__.py
petab/visualize/cli.py
petab/visualize/data_overview.py
petab/visualize/helper_functions.py
petab/visualize/lint.py
petab/visualize/plot_data_and_simulation.py
petab/visualize/plot_residuals.py
petab/visualize/plotter.py
petab/visualize/plotting.py
petab/visualize/templates/mystyle.css
petab/visualize/templates/report.html
petab-0.2.1.dist-info/LICENSE
petab-0.2.1.dist-info/METADATA
petab-0.2.1.dist-info/WHEEL
petab-0.2.1.dist-info/entry_points.txt
petab-0.2.1.dist-info/top_level.txt
petab-0.2.1.dist-info/RECORD
