Metadata-Version: 2.1
Name: petab
Version: 0.2.1
Summary: Parameter estimation tabular data
Home-page: https://github.com/PEtab-dev/libpetab-python
Author: The PEtab developers
Author-email: daniel.weindl@helmholtz-muenchen.de
Requires-Python: >=3.9.0
License-File: LICENSE
Requires-Dist: numpy (>=1.15.1)
Requires-Dist: pandas (>=1.2.0)
Requires-Dist: python-libsbml (>=5.17.0)
Requires-Dist: sympy
Requires-Dist: colorama
Requires-Dist: pyyaml
Requires-Dist: jsonschema
Provides-Extra: combine
Requires-Dist: python-libcombine (>=0.2.6) ; extra == 'combine'
Provides-Extra: doc
Requires-Dist: sphinx (!=5.1.0,>=3.5.3) ; extra == 'doc'
Requires-Dist: sphinxcontrib-napoleon (>=0.7) ; extra == 'doc'
Requires-Dist: sphinx-markdown-tables (>=0.0.15) ; extra == 'doc'
Requires-Dist: sphinx-rtd-theme (>=0.5.1) ; extra == 'doc'
Requires-Dist: m2r2 ; extra == 'doc'
Requires-Dist: myst-nb (>=0.14.0) ; extra == 'doc'
Requires-Dist: ipython (!=8.7.0,>=7.21.0) ; extra == 'doc'
Provides-Extra: quality
Requires-Dist: flake8 (>=3.8.3) ; extra == 'quality'
Provides-Extra: reports
Requires-Dist: Jinja2 (==3.0.3) ; extra == 'reports'
Provides-Extra: tests
Requires-Dist: pytest ; extra == 'tests'
Requires-Dist: pytest-cov ; extra == 'tests'
Requires-Dist: simplesbml ; extra == 'tests'
Requires-Dist: scipy ; extra == 'tests'
Requires-Dist: pysb ; extra == 'tests'
Provides-Extra: vis
Requires-Dist: matplotlib (>=3.6.0) ; extra == 'vis'
Requires-Dist: seaborn ; extra == 'vis'
Requires-Dist: scipy ; extra == 'vis'
